{
  "count": 87448,
  "next": "https://api.rawg.io/api/games?exclude_additions=true&key=2819eab2d32e48c1a69ef08a38cbff2c&ordering=rating&page=2&page_size=18&platform=4&stores=1",
  "previous": null,
  "results": [
    {
      "slug": "dont-drop-the-bass",
      "name": "Don't Drop the Bass",
      "playtime": 3,
      "platforms": [
        {
          "platform": {
            "id": 4,
            "name": "PC",
            "slug": "pc"
          }
        },
        {
          "platform": {
            "id": 5,
            "name": "macOS",
            "slug": "macos"
          }
        }
      ],
      "stores": [
        {
          "store": {
            "id": 1,
            "name": "Steam",
            "slug": "steam"
          }
        }
      ],
      "released": "2017-03-17",
      "tba": false,
      "background_image": "https://media.rawg.io/media/screenshots/b9f/b9f788d5d54a29018f92c92ae6dba89e.jpg",
      "rating": 0.0,
      "rating_top": 0,
      "ratings": [
        {
          "id": 3,
          "title": "meh",
          "count": 1,
          "percent": 100.0
        }
      ],
      "ratings_count": 1,
      "reviews_text_count": 0,
      "added": 1,
      "added_by_status": {
        "owned": 1
      },
      "metacritic": null,
      "suggestions_count": 216,
      "updated": "2019-08-28T22:13:34",
      "id": 11966,
      "score": null,
      "clip": null,
      "tags": [
        {
          "id": 40836,
          "name": "Full controller support",
          "slug": "full-controller-support",
          "language": "eng",
          "games_count": 9473,
          "image_background": "https://media.rawg.io/media/games/310/3106b0e012271c5ffb16497b070be739.jpg"
        },
        {
          "id": 40847,
          "name": "Steam Achievements",
          "slug": "steam-achievements",
          "language": "eng",
          "games_count": 20092,
          "image_background": "https://media.rawg.io/media/games/d1a/d1a2e99ade53494c6330a0ed945fe823.jpg"
        },
        {
          "id": 40850,
          "name": "Steam Leaderboards",
          "slug": "steam-leaderboards",
          "language": "eng",
          "games_count": 4409,
          "image_background": "https://media.rawg.io/media/games/aa3/aa36ba4b486a03ddfaef274fb4f5afd4.jpg"
        },
        {
          "id": 75,
          "name": "Local Co-Op",
          "slug": "local-co-op",
          "language": "eng",
          "games_count": 3520,
          "image_background": "https://media.rawg.io/media/games/e0f/e0f05a97ff926acf4c8f43e0849b6832.jpg"
        },
        {
          "id": 72,
          "name": "Local Multiplayer",
          "slug": "local-multiplayer",
          "language": "eng",
          "games_count": 8774,
          "image_background": "https://media.rawg.io/media/games/388/388935d851846f8ec747fffc7c765800.jpg"
        },
        {
          "id": 31,
          "name": "Singleplayer",
          "slug": "singleplayer",
          "language": "eng",
          "games_count": 94283,
          "image_background": "https://media.rawg.io/media/games/b7d/b7d3f1715fa8381a4e780173a197a615.jpg"
        },
        {
          "id": 198,
          "name": "Split Screen",
          "slug": "split-screen",
          "language": "eng",
          "games_count": 3769,
          "image_background": "https://media.rawg.io/media/screenshots/f2f/f2f3c93d6153da7aee590f3ab8ccd803.jpg"
        },
        {
          "id": 42398,
          "name": "Инди",
          "slug": "indi-2",
          "language": "rus",
          "games_count": 32347,
          "image_background": "https://media.rawg.io/media/games/ed5/ed5b7d01dd68fd8d598c91ad61f153af.jpg"
        },
        {
          "id": 42399,
          "name": "Казуальная игра",
          "slug": "kazualnaia-igra",
          "language": "rus",
          "games_count": 17983,
          "image_background": "https://media.rawg.io/media/games/e9c/e9c042d14515eb3ff7cb4db9fe78e435.jpg"
        },
        {
          "id": 42531,
          "name": "Спортивная игра",
          "slug": "sportivnaia-igra",
          "language": "rus",
          "games_count": 2257,
          "image_background": "https://media.rawg.io/media/games/d16/d160819f22de73d29813f7b6dad815f9.jpg"
        }
      ],
      "esrb_rating": null,
      "user_game": null,
      "reviews_count": 1,
      "community_rating": 0,
      "saturated_color": "0f0f0f",
      "dominant_color": "0f0f0f",
      "short_screenshots": [
        {
          "id": -1,
          "image": "https://media.rawg.io/media/screenshots/b9f/b9f788d5d54a29018f92c92ae6dba89e.jpg"
        },
        {
          "id": 99076,
          "image": "https://media.rawg.io/media/screenshots/dad/dadc85b8048836421ad1753d94e73d9f.jpg"
        },
        {
          "id": 99077,
          "image": "https://media.rawg.io/media/screenshots/dbc/dbc14a29191cd5716659c11043de1362.jpg"
        },
        {
          "id": 99078,
          "image": "https://media.rawg.io/media/screenshots/138/13896d4171e5bb414bc2259aca154337.jpg"
        },
        {
          "id": 99079,
          "image": "https://media.rawg.io/media/screenshots/301/30140d1340482dbbae51836dda7669c4.jpg"
        },
        {
          "id": 99080,
          "image": "https://media.rawg.io/media/screenshots/732/732c8c3a570904a5df238f5bf38d6871.jpg"
        },
        {
          "id": 99081,
          "image": "https://media.rawg.io/media/screenshots/eec/eec05a8a111739f7aa010d9548fd3ba2.jpg"
        }
      ],
      "parent_platforms": [
        {
          "platform": {
            "id": 1,
            "name": "PC",
            "slug": "pc"
          }
        },
        {
          "platform": {
            "id": 5,
            "name": "Apple Macintosh",
            "slug": "mac"
          }
        }
      ],
      "genres": [
        {
          "id": 40,
          "name": "Casual",
          "slug": "casual"
        },
        {
          "id": 51,
          "name": "Indie",
          "slug": "indie"
        },
        {
          "id": 15,
          "name": "Sports",
          "slug": "sports"
        }
      ]
    },
    {
      "slug": "constellation-distantia",
      "name": "Constellation Distantia",
      "playtime": 2,
      "platforms": [
        {
          "platform": {
            "id": 4,
            "name": "PC",
            "slug": "pc"
          }
        }
      ],
      "stores": [
        {
          "store": {
            "id": 1,
            "name": "Steam",
            "slug": "steam"
          }
        }
      ],
      "released": "2017-02-28",
      "tba": false,
      "background_image": "https://media.rawg.io/media/screenshots/114/1145c6dee628dbd8fb77fda0c227e064.jpg",
      "rating": 0.0,
      "rating_top": 0,
      "ratings": [],
      "ratings_count": 0,
      "reviews_text_count": 0,
      "added": 7,
      "added_by_status": {
        "yet": 1,
        "owned": 6
      },
      "metacritic": null,
      "suggestions_count": 352,
      "updated": "2019-08-28T22:13:30",
      "id": 12078,
      "score": null,
      "clip": null,
      "tags": [
        {
          "id": 69,
          "name": "Action-Adventure",
          "slug": "action-adventure",
          "language": "eng",
          "games_count": 6387,
          "image_background": "https://media.rawg.io/media/games/c50/c5085506fe4b5e20fc7aa5ace842c20b.jpg"
        },
        {
          "id": 40845,
          "name": "Partial Controller Support",
          "slug": "partial-controller-support",
          "language": "eng",
          "games_count": 6822,
          "image_background": "https://media.rawg.io/media/games/995/9951d9d55323d08967640f7b9ab3e342.jpg"
        },
        {
          "id": 40849,
          "name": "Steam Cloud",
          "slug": "steam-cloud",
          "language": "eng",
          "games_count": 9361,
          "image_background": "https://media.rawg.io/media/games/328/3283617cb7d75d67257fc58339188742.jpg"
        },
        {
          "id": 32,
          "name": "Sci-fi",
          "slug": "sci-fi",
          "language": "eng",
          "games_count": 8531,
          "image_background": "https://media.rawg.io/media/games/120/1201a40e4364557b124392ee50317b99.jpg"
        },
        {
          "id": 31,
          "name": "Singleplayer",
          "slug": "singleplayer",
          "language": "eng",
          "games_count": 94283,
          "image_background": "https://media.rawg.io/media/games/b7d/b7d3f1715fa8381a4e780173a197a615.jpg"
        },
        {
          "id": 25,
          "name": "Space",
          "slug": "space",
          "language": "eng",
          "games_count": 23212,
          "image_background": "https://media.rawg.io/media/games/ebd/ebdbb7eb52bd58b0e7fa4538d9757b60.jpg"
        },
        {
          "id": 1,
          "name": "Survival",
          "slug": "survival",
          "language": "eng",
          "games_count": 4132,
          "image_background": "https://media.rawg.io/media/games/48e/48e63bbddeddbe9ba81942772b156664.jpg"
        },
        {
          "id": 33,
          "name": "VR",
          "slug": "vr",
          "language": "eng",
          "games_count": 7848,
          "image_background": "https://media.rawg.io/media/games/58a/58ac7f6569259dcc0b60b921869b19fc.jpg"
        },
        {
          "id": 42392,
          "name": "Приключение",
          "slug": "prikliuchenie",
          "language": "rus",
          "games_count": 18381,
          "image_background": "https://media.rawg.io/media/games/bc0/bc06a29ceac58652b684deefe7d56099.jpg"
        },
        {
          "id": 42398,
          "name": "Инди",
          "slug": "indi-2",
          "language": "rus",
          "games_count": 32347,
          "image_background": "https://media.rawg.io/media/games/ed5/ed5b7d01dd68fd8d598c91ad61f153af.jpg"
        },
        {
          "id": 42417,
          "name": "Экшен",
          "slug": "ekshen",
          "language": "rus",
          "games_count": 20346,
          "image_background": "https://media.rawg.io/media/games/b8c/b8c243eaa0fbac8115e0cdccac3f91dc.jpg"
        },
        {
          "id": 42421,
          "name": "Стратегия",
          "slug": "strategiia",
          "language": "rus",
          "games_count": 9323,
          "image_background": "https://media.rawg.io/media/games/879/879c930f9c6787c920153fa2df452eb3.jpg"
        },
        {
          "id": 42422,
          "name": "Космос",
          "slug": "kosmos-2",
          "language": "rus",
          "games_count": 1538,
          "image_background": "https://media.rawg.io/media/screenshots/120/120d930368bc171c42f9caab94e33c65.jpg"
        },
        {
          "id": 42423,
          "name": "Научная фантастика",
          "slug": "nauchnaia-fantastika",
          "language": "rus",
          "games_count": 2851,
          "image_background": "https://media.rawg.io/media/games/9dd/9ddabb34840ea9227556670606cf8ea3.jpg"
        },
        {
          "id": 42452,
          "name": "Выживание",
          "slug": "vyzhivanie",
          "language": "rus",
          "games_count": 2260,
          "image_background": "https://media.rawg.io/media/games/d9f/d9f982e042df6263684ba1fdea3efc1c.jpg"
        },
        {
          "id": 42490,
          "name": "Приключенческий экшен",
          "slug": "prikliuchencheskii-ekshen",
          "language": "rus",
          "games_count": 1155,
          "image_background": "https://media.rawg.io/media/games/473/473bd9a5e9522629d6cb28b701fb836a.jpg"
        }
      ],
      "esrb_rating": null,
      "user_game": null,
      "reviews_count": 0,
      "community_rating": 0,
      "saturated_color": "0f0f0f",
      "dominant_color": "0f0f0f",
      "short_screenshots": [
        {
          "id": -1,
          "image": "https://media.rawg.io/media/screenshots/114/1145c6dee628dbd8fb77fda0c227e064.jpg"
        },
        {
          "id": 100482,
          "image": "https://media.rawg.io/media/screenshots/d71/d718f702fd1d79b6ade291d43238c54e.jpg"
        },
        {
          "id": 100483,
          "image": "https://media.rawg.io/media/screenshots/667/667e305a522ef1a4f8d061b68f60f5fb.jpg"
        },
        {
          "id": 100484,
          "image": "https://media.rawg.io/media/screenshots/0c4/0c477a60fb947f32cee7c13e34190bdc.jpg"
        },
        {
          "id": 100485,
          "image": "https://media.rawg.io/media/screenshots/653/6538c257628fe837add8d6c856d534a4.jpg"
        },
        {
          "id": 100486,
          "image": "https://media.rawg.io/media/screenshots/58e/58e3b7b077ea809a3d05d71e238bf7cc.jpg"
        },
        {
          "id": 100487,
          "image": "https://media.rawg.io/media/screenshots/e23/e2321f829de0948e320fc31f33a93d58.jpg"
        }
      ],
      "parent_platforms": [
        {
          "platform": {
            "id": 1,
            "name": "PC",
            "slug": "pc"
          }
        }
      ],
      "genres": [
        {
          "id": 51,
          "name": "Indie",
          "slug": "indie"
        },
        {
          "id": 10,
          "name": "Strategy",
          "slug": "strategy"
        },
        {
          "id": 3,
          "name": "Adventure",
          "slug": "adventure"
        },
        {
          "id": 4,
          "name": "Action",
          "slug": "action"
        }
      ]
    },
    {
      "slug": "the-body-vr-anatomy-viewer",
      "name": "The Body VR: Anatomy Viewer",
      "playtime": 1,
      "platforms": [
        {
          "platform": {
            "id": 4,
            "name": "PC",
            "slug": "pc"
          }
        }
      ],
      "stores": [
        {
          "store": {
            "id": 1,
            "name": "Steam",
            "slug": "steam"
          }
        }
      ],
      "released": "2017-03-01",
      "tba": false,
      "background_image": "https://media.rawg.io/media/screenshots/1e5/1e539e03b69c8a54ad635e9f7c53e2e3.jpg",
      "rating": 0.0,
      "rating_top": 0,
      "ratings": [],
      "ratings_count": 0,
      "reviews_text_count": 0,
      "added": 1,
      "added_by_status": {
        "owned": 1
      },
      "metacritic": null,
      "suggestions_count": 156,
      "updated": "2019-01-09T12:41:06",
      "id": 12101,
      "score": null,
      "clip": null,
      "tags": [
        {
          "id": 86,
          "name": "Education",
          "slug": "education",
          "language": "eng",
          "games_count": 1042,
          "image_background": "https://media.rawg.io/media/screenshots/42d/42d770eb49f2ba01cd4045e0d92af7a9.jpg"
        },
        {
          "id": 173,
          "name": "Utilities",
          "slug": "utilities",
          "language": "eng",
          "games_count": 217,
          "image_background": "https://media.rawg.io/media/screenshots/570/5705c9dd0864bfae51c463672110c1e4.jpg"
        }
      ],
      "esrb_rating": null,
      "user_game": null,
      "reviews_count": 0,
      "community_rating": 0,
      "saturated_color": "0f0f0f",
      "dominant_color": "0f0f0f",
      "short_screenshots": [
        {
          "id": -1,
          "image": "https://media.rawg.io/media/screenshots/1e5/1e539e03b69c8a54ad635e9f7c53e2e3.jpg"
        },
        {
          "id": 100718,
          "image": "https://media.rawg.io/media/screenshots/ec1/ec1ba8000f64a0720880b872c454cfbe.jpg"
        },
        {
          "id": 100719,
          "image": "https://media.rawg.io/media/screenshots/b6a/b6ad7d0d37d840c212c55147c229c588.jpg"
        },
        {
          "id": 100720,
          "image": "https://media.rawg.io/media/screenshots/46f/46f3864cec41487f71b00db823cb5b68.jpg"
        },
        {
          "id": 100721,
          "image": "https://media.rawg.io/media/screenshots/c5a/c5a026aa07cb87249eab2d7c2fd14da7.jpg"
        },
        {
          "id": 100722,
          "image": "https://media.rawg.io/media/screenshots/f91/f91a55ff03eb1b39ec219b82c980601d.jpg"
        },
        {
          "id": 100723,
          "image": "https://media.rawg.io/media/screenshots/1e5/1e539e03b69c8a54ad635e9f7c53e2e3.jpg"
        }
      ],
      "parent_platforms": [
        {
          "platform": {
            "id": 1,
            "name": "PC",
            "slug": "pc"
          }
        }
      ],
      "genres": [
        {
          "id": 34,
          "name": "Educational",
          "slug": "educational"
        }
      ]
    },
    {
      "slug": "adventures-of-hooi",
      "name": "Adventures of Hooi",
      "playtime": 5,
      "platforms": [
        {
          "platform": {
            "id": 4,
            "name": "PC",
            "slug": "pc"
          }
        }
      ],
      "stores": [
        {
          "store": {
            "id": 1,
            "name": "Steam",
            "slug": "steam"
          }
        }
      ],
      "released": "2016-12-02",
      "tba": false,
      "background_image": "https://media.rawg.io/media/screenshots/19f/19f5a571bbbbb0979e417fddf5962cc7.jpg",
      "rating": 0.0,
      "rating_top": 0,
      "ratings": [],
      "ratings_count": 0,
      "reviews_text_count": 0,
      "added": 10,
      "added_by_status": {
        "owned": 10
      },
      "metacritic": null,
      "suggestions_count": 183,
      "updated": "2019-08-28T22:13:28",
      "id": 12151,
      "score": null,
      "clip": null,
      "tags": [
        {
          "id": 31,
          "name": "Singleplayer",
          "slug": "singleplayer",
          "language": "eng",
          "games_count": 94283,
          "image_background": "https://media.rawg.io/media/games/b7d/b7d3f1715fa8381a4e780173a197a615.jpg"
        },
        {
          "id": 7808,
          "name": "steam-trading-cards",
          "slug": "steam-trading-cards",
          "language": "eng",
          "games_count": 7605,
          "image_background": "https://media.rawg.io/media/games/d1a/d1a2e99ade53494c6330a0ed945fe823.jpg"
        }
      ],
      "esrb_rating": null,
      "user_game": null,
      "reviews_count": 0,
      "community_rating": 0,
      "saturated_color": "0f0f0f",
      "dominant_color": "0f0f0f",
      "short_screenshots": [
        {
          "id": -1,
          "image": "https://media.rawg.io/media/screenshots/19f/19f5a571bbbbb0979e417fddf5962cc7.jpg"
        },
        {
          "id": 101171,
          "image": "https://media.rawg.io/media/screenshots/045/045004942a51f9f17cc738b67b0614c4.jpg"
        },
        {
          "id": 101172,
          "image": "https://media.rawg.io/media/screenshots/134/13441973cabf79d980735689dbb8a328.jpg"
        },
        {
          "id": 101173,
          "image": "https://media.rawg.io/media/screenshots/1c8/1c8417500446b0715a6c52a9920b9ef3.jpg"
        },
        {
          "id": 101174,
          "image": "https://media.rawg.io/media/screenshots/c0d/c0d5b7208b26bd930143796892494700.jpg"
        },
        {
          "id": 101175,
          "image": "https://media.rawg.io/media/screenshots/f74/f74f34d4a29d3818c91da951c2e9e5eb.jpg"
        },
        {
          "id": 101176,
          "image": "https://media.rawg.io/media/screenshots/9ab/9abf0aa06ce1a70efda502e67ca67a10.jpg"
        }
      ],
      "parent_platforms": [
        {
          "platform": {
            "id": 1,
            "name": "PC",
            "slug": "pc"
          }
        }
      ],
      "genres": [
        {
          "id": 3,
          "name": "Adventure",
          "slug": "adventure"
        }
      ]
    },
    {
      "slug": "4x4-offroad-racing-nitro",
      "name": "4x4 Offroad Racing - Nitro",
      "playtime": 0,
      "platforms": [
        {
          "platform": {
            "id": 4,
            "name": "PC",
            "slug": "pc"
          }
        }
      ],
      "stores": [
        {
          "store": {
            "id": 1,
            "name": "Steam",
            "slug": "steam"
          }
        }
      ],
      "released": "2017-03-10",
      "tba": false,
      "background_image": "https://media.rawg.io/media/screenshots/254/254e1f918b57a7ee903e2de0c7c45f9b.jpg",
      "rating": 0.0,
      "rating_top": 0,
      "ratings": [],
      "ratings_count": 0,
      "reviews_text_count": 0,
      "added": 0,
      "added_by_status": null,
      "metacritic": null,
      "suggestions_count": 412,
      "updated": "2019-08-28T22:13:27",
      "id": 12172,
      "score": null,
      "clip": null,
      "tags": [
        {
          "id": 40845,
          "name": "Partial Controller Support",
          "slug": "partial-controller-support",
          "language": "eng",
          "games_count": 6822,
          "image_background": "https://media.rawg.io/media/games/995/9951d9d55323d08967640f7b9ab3e342.jpg"
        },
        {
          "id": 40849,
          "name": "Steam Cloud",
          "slug": "steam-cloud",
          "language": "eng",
          "games_count": 9361,
          "image_background": "https://media.rawg.io/media/games/328/3283617cb7d75d67257fc58339188742.jpg"
        },
        {
          "id": 72,
          "name": "Local Multiplayer",
          "slug": "local-multiplayer",
          "language": "eng",
          "games_count": 8774,
          "image_background": "https://media.rawg.io/media/games/388/388935d851846f8ec747fffc7c765800.jpg"
        },
        {
          "id": 7,
          "name": "Multiplayer",
          "slug": "multiplayer",
          "language": "eng",
          "games_count": 22719,
          "image_background": "https://media.rawg.io/media/games/34b/34b1f1850a1c06fd971bc6ab3ac0ce0e.jpg"
        },
        {
          "id": 31,
          "name": "Singleplayer",
          "slug": "singleplayer",
          "language": "eng",
          "games_count": 94283,
          "image_background": "https://media.rawg.io/media/games/b7d/b7d3f1715fa8381a4e780173a197a615.jpg"
        },
        {
          "id": 397,
          "name": "Online multiplayer",
          "slug": "online-multiplayer",
          "language": "eng",
          "games_count": 3793,
          "image_background": "https://media.rawg.io/media/games/98c/98cd77a9f61b31a6ddab1670b079c841.jpg"
        },
        {
          "id": 42413,
          "name": "Симулятор",
          "slug": "simuliator",
          "language": "rus",
          "games_count": 9279,
          "image_background": "https://media.rawg.io/media/games/174/1743b3dd185bda4a7be349347d4064df.jpg"
        },
        {
          "id": 42496,
          "name": "Гонки",
          "slug": "gonki",
          "language": "rus",
          "games_count": 1762,
          "image_background": "https://media.rawg.io/media/games/1f5/1f5ddf7199f2778ff83663b93b5cb330.jpg"
        },
        {
          "id": 42531,
          "name": "Спортивная игра",
          "slug": "sportivnaia-igra",
          "language": "rus",
          "games_count": 2257,
          "image_background": "https://media.rawg.io/media/games/d16/d160819f22de73d29813f7b6dad815f9.jpg"
        }
      ],
      "esrb_rating": null,
      "user_game": null,
      "reviews_count": 0,
      "community_rating": 0,
      "saturated_color": "0f0f0f",
      "dominant_color": "0f0f0f",
      "short_screenshots": [
        {
          "id": -1,
          "image": "https://media.rawg.io/media/screenshots/254/254e1f918b57a7ee903e2de0c7c45f9b.jpg"
        },
        {
          "id": 101372,
          "image": "https://media.rawg.io/media/screenshots/997/997a9170562fe7628559b70feee24ea2.jpg"
        },
        {
          "id": 101373,
          "image": "https://media.rawg.io/media/screenshots/924/92460b4435f223e3b84eb024387f669c.jpg"
        },
        {
          "id": 101374,
          "image": "https://media.rawg.io/media/screenshots/8fb/8fb3269bdb1cd3f4f41ee6e731f4960d.jpg"
        },
        {
          "id": 101375,
          "image": "https://media.rawg.io/media/screenshots/7c5/7c54a58e86c8697038d286d15025dc6e.jpg"
        },
        {
          "id": 101376,
          "image": "https://media.rawg.io/media/screenshots/663/6638627c29c1208b92f969b8afcb2723.jpg"
        },
        {
          "id": 101377,
          "image": "https://media.rawg.io/media/screenshots/cae/caee07a0bd7310561cd371743b77d7c1.jpg"
        }
      ],
      "parent_platforms": [
        {
          "platform": {
            "id": 1,
            "name": "PC",
            "slug": "pc"
          }
        }
      ],
      "genres": [
        {
          "id": 1,
          "name": "Racing",
          "slug": "racing"
        },
        {
          "id": 14,
          "name": "Simulation",
          "slug": "simulation"
        },
        {
          "id": 15,
          "name": "Sports",
          "slug": "sports"
        }
      ]
    },
    {
      "slug": "planetfate",
      "name": "PlanetFate",
      "playtime": 0,
      "platforms": [
        {
          "platform": {
            "id": 4,
            "name": "PC",
            "slug": "pc"
          }
        }
      ],
      "stores": [
        {
          "store": {
            "id": 1,
            "name": "Steam",
            "slug": "steam"
          }
        }
      ],
      "released": "2016-06-06",
      "tba": false,
      "background_image": "https://media.rawg.io/media/screenshots/1ab/1ab79987fb7a6d8354810f491d8bc2ad.jpg",
      "rating": 0.0,
      "rating_top": 0,
      "ratings": [],
      "ratings_count": 0,
      "reviews_text_count": 0,
      "added": 0,
      "added_by_status": null,
      "metacritic": null,
      "suggestions_count": 342,
      "updated": "2019-08-28T22:13:25",
      "id": 12217,
      "score": null,
      "clip": null,
      "tags": [
        {
          "id": 14,
          "name": "Early Access",
          "slug": "early-access",
          "language": "eng",
          "games_count": 7090,
          "image_background": "https://media.rawg.io/media/screenshots/654/6540928602af293014efa90d75c420b7.jpg"
        },
        {
          "id": 31,
          "name": "Singleplayer",
          "slug": "singleplayer",
          "language": "eng",
          "games_count": 94283,
          "image_background": "https://media.rawg.io/media/games/b7d/b7d3f1715fa8381a4e780173a197a615.jpg"
        },
        {
          "id": 33,
          "name": "VR",
          "slug": "vr",
          "language": "eng",
          "games_count": 7848,
          "image_background": "https://media.rawg.io/media/games/58a/58ac7f6569259dcc0b60b921869b19fc.jpg"
        },
        {
          "id": 42398,
          "name": "Инди",
          "slug": "indi-2",
          "language": "rus",
          "games_count": 32347,
          "image_background": "https://media.rawg.io/media/games/ed5/ed5b7d01dd68fd8d598c91ad61f153af.jpg"
        },
        {
          "id": 42411,
          "name": "Ранний доступ",
          "slug": "rannii-dostup",
          "language": "rus",
          "games_count": 6608,
          "image_background": "https://media.rawg.io/media/games/e4a/e4ab7f784bdc38c76ce6e4cef9715d18.jpg"
        },
        {
          "id": 42417,
          "name": "Экшен",
          "slug": "ekshen",
          "language": "rus",
          "games_count": 20346,
          "image_background": "https://media.rawg.io/media/games/b8c/b8c243eaa0fbac8115e0cdccac3f91dc.jpg"
        },
        {
          "id": 42421,
          "name": "Стратегия",
          "slug": "strategiia",
          "language": "rus",
          "games_count": 9323,
          "image_background": "https://media.rawg.io/media/games/879/879c930f9c6787c920153fa2df452eb3.jpg"
        }
      ],
      "esrb_rating": null,
      "user_game": null,
      "reviews_count": 0,
      "community_rating": 0,
      "saturated_color": "0f0f0f",
      "dominant_color": "0f0f0f",
      "short_screenshots": [
        {
          "id": -1,
          "image": "https://media.rawg.io/media/screenshots/1ab/1ab79987fb7a6d8354810f491d8bc2ad.jpg"
        },
        {
          "id": 101835,
          "image": "https://media.rawg.io/media/screenshots/4ed/4edf5e1dd6f703ed37c5b9f5219f77f6.jpg"
        },
        {
          "id": 101836,
          "image": "https://media.rawg.io/media/screenshots/df8/df8516137dc2b7e1f5c68458d7e274ba.jpg"
        },
        {
          "id": 101837,
          "image": "https://media.rawg.io/media/screenshots/aea/aea2b0d18dfda3bb93f1b7cf22925411.jpg"
        },
        {
          "id": 101838,
          "image": "https://media.rawg.io/media/screenshots/b84/b8424d7441ae438f5dd12e0c4c8d6052.jpg"
        },
        {
          "id": 101839,
          "image": "https://media.rawg.io/media/screenshots/6d2/6d241db59262b1f611ac5118b8729d83.jpg"
        },
        {
          "id": 101840,
          "image": "https://media.rawg.io/media/screenshots/a1f/a1f9fb8185f8e1b4b0eb31dc8f89372f.jpg"
        }
      ],
      "parent_platforms": [
        {
          "platform": {
            "id": 1,
            "name": "PC",
            "slug": "pc"
          }
        }
      ],
      "genres": [
        {
          "id": 10,
          "name": "Strategy",
          "slug": "strategy"
        },
        {
          "id": 51,
          "name": "Indie",
          "slug": "indie"
        },
        {
          "id": 4,
          "name": "Action",
          "slug": "action"
        }
      ]
    },
    {
      "slug": "arena-master",
      "name": "Arena Master",
      "playtime": 0,
      "platforms": [
        {
          "platform": {
            "id": 4,
            "name": "PC",
            "slug": "pc"
          }
        }
      ],
      "stores": [
        {
          "store": {
            "id": 1,
            "name": "Steam",
            "slug": "steam"
          }
        }
      ],
      "released": "2016-11-17",
      "tba": false,
      "background_image": "https://media.rawg.io/media/screenshots/9b1/9b11b56c5b5c7ee195744ecbc40dd6d1.jpg",
      "rating": 0.0,
      "rating_top": 0,
      "ratings": [],
      "ratings_count": 0,
      "reviews_text_count": 0,
      "added": 0,
      "added_by_status": null,
      "metacritic": null,
      "suggestions_count": 448,
      "updated": "2019-08-28T22:13:19",
      "id": 12363,
      "score": null,
      "clip": null,
      "tags": [
        {
          "id": 14,
          "name": "Early Access",
          "slug": "early-access",
          "language": "eng",
          "games_count": 7090,
          "image_background": "https://media.rawg.io/media/screenshots/654/6540928602af293014efa90d75c420b7.jpg"
        },
        {
          "id": 31,
          "name": "Singleplayer",
          "slug": "singleplayer",
          "language": "eng",
          "games_count": 94283,
          "image_background": "https://media.rawg.io/media/games/b7d/b7d3f1715fa8381a4e780173a197a615.jpg"
        },
        {
          "id": 34,
          "name": "Violent",
          "slug": "violent",
          "language": "eng",
          "games_count": 4087,
          "image_background": "https://media.rawg.io/media/games/569/56978b5a77f13aa2ec5d09ec81d01cad.jpg"
        },
        {
          "id": 33,
          "name": "VR",
          "slug": "vr",
          "language": "eng",
          "games_count": 7848,
          "image_background": "https://media.rawg.io/media/games/58a/58ac7f6569259dcc0b60b921869b19fc.jpg"
        },
        {
          "id": 42398,
          "name": "Инди",
          "slug": "indi-2",
          "language": "rus",
          "games_count": 32347,
          "image_background": "https://media.rawg.io/media/games/ed5/ed5b7d01dd68fd8d598c91ad61f153af.jpg"
        },
        {
          "id": 42402,
          "name": "Насилие",
          "slug": "nasilie",
          "language": "rus",
          "games_count": 3367,
          "image_background": "https://media.rawg.io/media/games/5fa/5fae5fec3c943179e09da67a4427d68f.jpg"
        },
        {
          "id": 42411,
          "name": "Ранний доступ",
          "slug": "rannii-dostup",
          "language": "rus",
          "games_count": 6608,
          "image_background": "https://media.rawg.io/media/games/e4a/e4ab7f784bdc38c76ce6e4cef9715d18.jpg"
        },
        {
          "id": 42417,
          "name": "Экшен",
          "slug": "ekshen",
          "language": "rus",
          "games_count": 20346,
          "image_background": "https://media.rawg.io/media/games/b8c/b8c243eaa0fbac8115e0cdccac3f91dc.jpg"
        }
      ],
      "esrb_rating": null,
      "user_game": null,
      "reviews_count": 0,
      "community_rating": 0,
      "saturated_color": "0f0f0f",
      "dominant_color": "0f0f0f",
      "short_screenshots": [
        {
          "id": -1,
          "image": "https://media.rawg.io/media/screenshots/9b1/9b11b56c5b5c7ee195744ecbc40dd6d1.jpg"
        },
        {
          "id": 103445,
          "image": "https://media.rawg.io/media/screenshots/def/deff09bbde106fdf48b49082d020db3c.jpg"
        },
        {
          "id": 103446,
          "image": "https://media.rawg.io/media/screenshots/a50/a5093c1d06c75be3e7aa06faaba04888.jpg"
        },
        {
          "id": 103447,
          "image": "https://media.rawg.io/media/screenshots/8d7/8d738a703a49d4dd3f0fd14f0c98b662.jpg"
        },
        {
          "id": 103448,
          "image": "https://media.rawg.io/media/screenshots/31d/31da304aa61b46145298a83e15427afd.jpg"
        },
        {
          "id": 103449,
          "image": "https://media.rawg.io/media/screenshots/db5/db5a295421081c45d6a40e579b921866.jpg"
        },
        {
          "id": 103450,
          "image": "https://media.rawg.io/media/screenshots/58e/58eda066f30237f2c6ad818f0e9f3f6d.jpg"
        }
      ],
      "parent_platforms": [
        {
          "platform": {
            "id": 1,
            "name": "PC",
            "slug": "pc"
          }
        }
      ],
      "genres": [
        {
          "id": 51,
          "name": "Indie",
          "slug": "indie"
        },
        {
          "id": 4,
          "name": "Action",
          "slug": "action"
        }
      ]
    },
    {
      "slug": "scs-deorbit",
      "name": "SCS deORBIT",
      "playtime": 0,
      "platforms": [
        {
          "platform": {
            "id": 4,
            "name": "PC",
            "slug": "pc"
          }
        },
        {
          "platform": {
            "id": 6,
            "name": "Linux",
            "slug": "linux"
          }
        }
      ],
      "stores": [
        {
          "store": {
            "id": 1,
            "name": "Steam",
            "slug": "steam"
          }
        }
      ],
      "released": "2015-08-17",
      "tba": false,
      "background_image": "https://media.rawg.io/media/screenshots/327/327c00373dadd8500282ec36633e998f.jpg",
      "rating": 0.0,
      "rating_top": 0,
      "ratings": [],
      "ratings_count": 0,
      "reviews_text_count": 0,
      "added": 5,
      "added_by_status": {
        "owned": 5
      },
      "metacritic": null,
      "suggestions_count": 402,
      "updated": "2019-08-28T22:13:18",
      "id": 12413,
      "score": null,
      "clip": null,
      "tags": [
        {
          "id": 40836,
          "name": "Full controller support",
          "slug": "full-controller-support",
          "language": "eng",
          "games_count": 9473,
          "image_background": "https://media.rawg.io/media/games/310/3106b0e012271c5ffb16497b070be739.jpg"
        },
        {
          "id": 40847,
          "name": "Steam Achievements",
          "slug": "steam-achievements",
          "language": "eng",
          "games_count": 20092,
          "image_background": "https://media.rawg.io/media/games/d1a/d1a2e99ade53494c6330a0ed945fe823.jpg"
        },
        {
          "id": 40849,
          "name": "Steam Cloud",
          "slug": "steam-cloud",
          "language": "eng",
          "games_count": 9361,
          "image_background": "https://media.rawg.io/media/games/328/3283617cb7d75d67257fc58339188742.jpg"
        },
        {
          "id": 31,
          "name": "Singleplayer",
          "slug": "singleplayer",
          "language": "eng",
          "games_count": 94283,
          "image_background": "https://media.rawg.io/media/games/b7d/b7d3f1715fa8381a4e780173a197a615.jpg"
        },
        {
          "id": 42392,
          "name": "Приключение",
          "slug": "prikliuchenie",
          "language": "rus",
          "games_count": 18381,
          "image_background": "https://media.rawg.io/media/games/bc0/bc06a29ceac58652b684deefe7d56099.jpg"
        },
        {
          "id": 42398,
          "name": "Инди",
          "slug": "indi-2",
          "language": "rus",
          "games_count": 32347,
          "image_background": "https://media.rawg.io/media/games/ed5/ed5b7d01dd68fd8d598c91ad61f153af.jpg"
        },
        {
          "id": 42413,
          "name": "Симулятор",
          "slug": "simuliator",
          "language": "rus",
          "games_count": 9279,
          "image_background": "https://media.rawg.io/media/games/174/1743b3dd185bda4a7be349347d4064df.jpg"
        },
        {
          "id": 42417,
          "name": "Экшен",
          "slug": "ekshen",
          "language": "rus",
          "games_count": 20346,
          "image_background": "https://media.rawg.io/media/games/b8c/b8c243eaa0fbac8115e0cdccac3f91dc.jpg"
        }
      ],
      "esrb_rating": null,
      "user_game": null,
      "reviews_count": 0,
      "community_rating": 0,
      "saturated_color": "0f0f0f",
      "dominant_color": "0f0f0f",
      "short_screenshots": [
        {
          "id": -1,
          "image": "https://media.rawg.io/media/screenshots/327/327c00373dadd8500282ec36633e998f.jpg"
        },
        {
          "id": 103966,
          "image": "https://media.rawg.io/media/screenshots/e4b/e4b8b6a92eb260d8f579b15b0db049f7.jpg"
        },
        {
          "id": 103967,
          "image": "https://media.rawg.io/media/screenshots/8b7/8b733689649b1505cec7d8c6db24e772.jpg"
        },
        {
          "id": 103968,
          "image": "https://media.rawg.io/media/screenshots/0d1/0d1fa53618efe36d28d093156317fd48.jpg"
        },
        {
          "id": 103969,
          "image": "https://media.rawg.io/media/screenshots/ace/acec6fe0009ccc9df2f026d164f5c1b8.jpg"
        },
        {
          "id": 103970,
          "image": "https://media.rawg.io/media/screenshots/3f7/3f7a06ba2d15fe3ced6a4e37a0543f45.jpg"
        },
        {
          "id": 103971,
          "image": "https://media.rawg.io/media/screenshots/094/094ac948bbd9906dc798d51bf74a1170.jpg"
        }
      ],
      "parent_platforms": [
        {
          "platform": {
            "id": 1,
            "name": "PC",
            "slug": "pc"
          }
        },
        {
          "platform": {
            "id": 6,
            "name": "Linux",
            "slug": "linux"
          }
        }
      ],
      "genres": [
        {
          "id": 51,
          "name": "Indie",
          "slug": "indie"
        },
        {
          "id": 3,
          "name": "Adventure",
          "slug": "adventure"
        },
        {
          "id": 4,
          "name": "Action",
          "slug": "action"
        },
        {
          "id": 14,
          "name": "Simulation",
          "slug": "simulation"
        }
      ]
    },
    {
      "slug": "drift-7-islands-survival",
      "name": "Drift 7 Islands (survival)",
      "playtime": 1,
      "platforms": [
        {
          "platform": {
            "id": 4,
            "name": "PC",
            "slug": "pc"
          }
        }
      ],
      "stores": [
        {
          "store": {
            "id": 1,
            "name": "Steam",
            "slug": "steam"
          }
        }
      ],
      "released": "2017-03-06",
      "tba": false,
      "background_image": "https://media.rawg.io/media/screenshots/18b/18b8b8d85a94d442fccef77989cfa2bb.jpg",
      "rating": 0.0,
      "rating_top": 0,
      "ratings": [],
      "ratings_count": 0,
      "reviews_text_count": 0,
      "added": 15,
      "added_by_status": {
        "owned": 14,
        "dropped": 1
      },
      "metacritic": null,
      "suggestions_count": 52,
      "updated": "2019-08-28T22:13:17",
      "id": 12450,
      "score": null,
      "clip": null,
      "tags": [
        {
          "id": 24,
          "name": "RPG",
          "slug": "rpg",
          "language": "eng",
          "games_count": 10649,
          "image_background": "https://media.rawg.io/media/games/91c/91c4f377c1e09755b60a0102c5252843.jpg"
        },
        {
          "id": 31,
          "name": "Singleplayer",
          "slug": "singleplayer",
          "language": "eng",
          "games_count": 94283,
          "image_background": "https://media.rawg.io/media/games/b7d/b7d3f1715fa8381a4e780173a197a615.jpg"
        },
        {
          "id": 42392,
          "name": "Приключение",
          "slug": "prikliuchenie",
          "language": "rus",
          "games_count": 18381,
          "image_background": "https://media.rawg.io/media/games/bc0/bc06a29ceac58652b684deefe7d56099.jpg"
        },
        {
          "id": 42398,
          "name": "Инди",
          "slug": "indi-2",
          "language": "rus",
          "games_count": 32347,
          "image_background": "https://media.rawg.io/media/games/ed5/ed5b7d01dd68fd8d598c91ad61f153af.jpg"
        },
        {
          "id": 42412,
          "name": "Ролевая игра",
          "slug": "rolevaia-igra",
          "language": "rus",
          "games_count": 8129,
          "image_background": "https://media.rawg.io/media/games/83f/83f6f70a7c1b86cd2637b029d8b42caa.jpg"
        }
      ],
      "esrb_rating": null,
      "user_game": null,
      "reviews_count": 0,
      "community_rating": 0,
      "saturated_color": "0f0f0f",
      "dominant_color": "0f0f0f",
      "short_screenshots": [
        {
          "id": -1,
          "image": "https://media.rawg.io/media/screenshots/18b/18b8b8d85a94d442fccef77989cfa2bb.jpg"
        },
        {
          "id": 104338,
          "image": "https://media.rawg.io/media/screenshots/2ea/2ea13b177afdf23fbcc657fab71bd299.jpg"
        },
        {
          "id": 104339,
          "image": "https://media.rawg.io/media/screenshots/fd3/fd3c029fe0f081493248971675c374d5.jpg"
        },
        {
          "id": 104340,
          "image": "https://media.rawg.io/media/screenshots/03f/03fed096f7299ed730c84ae2d4242019.jpg"
        },
        {
          "id": 104341,
          "image": "https://media.rawg.io/media/screenshots/399/3995ee110aa551c2dbe47cafe26c8696.jpg"
        },
        {
          "id": 104342,
          "image": "https://media.rawg.io/media/screenshots/18b/18b8b8d85a94d442fccef77989cfa2bb.jpg"
        }
      ],
      "parent_platforms": [
        {
          "platform": {
            "id": 1,
            "name": "PC",
            "slug": "pc"
          }
        }
      ],
      "genres": [
        {
          "id": 51,
          "name": "Indie",
          "slug": "indie"
        },
        {
          "id": 3,
          "name": "Adventure",
          "slug": "adventure"
        },
        {
          "id": 5,
          "name": "RPG",
          "slug": "role-playing-games-rpg"
        }
      ]
    },
    {
      "slug": "tankyou",
      "name": "TankYou!",
      "playtime": 3,
      "platforms": [
        {
          "platform": {
            "id": 4,
            "name": "PC",
            "slug": "pc"
          }
        }
      ],
      "stores": [
        {
          "store": {
            "id": 1,
            "name": "Steam",
            "slug": "steam"
          }
        }
      ],
      "released": "2016-09-16",
      "tba": false,
      "background_image": "https://media.rawg.io/media/screenshots/a92/a92d6549a58f90cada80009c2f20e38c.jpg",
      "rating": 0.0,
      "rating_top": 0,
      "ratings": [
        {
          "id": 5,
          "title": "exceptional",
          "count": 1,
          "percent": 100.0
        }
      ],
      "ratings_count": 1,
      "reviews_text_count": 0,
      "added": 5,
      "added_by_status": {
        "owned": 5
      },
      "metacritic": null,
      "suggestions_count": 459,
      "updated": "2019-08-28T22:13:15",
      "id": 12478,
      "score": null,
      "clip": null,
      "tags": [
        {
          "id": 40836,
          "name": "Full controller support",
          "slug": "full-controller-support",
          "language": "eng",
          "games_count": 9473,
          "image_background": "https://media.rawg.io/media/games/310/3106b0e012271c5ffb16497b070be739.jpg"
        },
        {
          "id": 40847,
          "name": "Steam Achievements",
          "slug": "steam-achievements",
          "language": "eng",
          "games_count": 20092,
          "image_background": "https://media.rawg.io/media/games/d1a/d1a2e99ade53494c6330a0ed945fe823.jpg"
        },
        {
          "id": 40849,
          "name": "Steam Cloud",
          "slug": "steam-cloud",
          "language": "eng",
          "games_count": 9361,
          "image_background": "https://media.rawg.io/media/games/328/3283617cb7d75d67257fc58339188742.jpg"
        },
        {
          "id": 18,
          "name": "Co-op",
          "slug": "co-op",
          "language": "eng",
          "games_count": 5951,
          "image_background": "https://media.rawg.io/media/games/15c/15c95a4915f88a3e89c821526afe05fc.jpg"
        },
        {
          "id": 51,
          "name": "Destruction",
          "slug": "destruction",
          "language": "eng",
          "games_count": 2206,
          "image_background": "https://media.rawg.io/media/games/8bd/8bda6d876f3e241c6024022299553efd.jpg"
        },
        {
          "id": 75,
          "name": "Local Co-Op",
          "slug": "local-co-op",
          "language": "eng",
          "games_count": 3520,
          "image_background": "https://media.rawg.io/media/games/e0f/e0f05a97ff926acf4c8f43e0849b6832.jpg"
        },
        {
          "id": 31,
          "name": "Singleplayer",
          "slug": "singleplayer",
          "language": "eng",
          "games_count": 94283,
          "image_background": "https://media.rawg.io/media/games/b7d/b7d3f1715fa8381a4e780173a197a615.jpg"
        },
        {
          "id": 198,
          "name": "Split Screen",
          "slug": "split-screen",
          "language": "eng",
          "games_count": 3769,
          "image_background": "https://media.rawg.io/media/screenshots/f2f/f2f3c93d6153da7aee590f3ab8ccd803.jpg"
        },
        {
          "id": 55,
          "name": "Tanks",
          "slug": "tanks",
          "language": "eng",
          "games_count": 1871,
          "image_background": "https://media.rawg.io/media/screenshots/92e/92e1e8dd0b1fd2071d88c91590b72b3b.jpg"
        },
        {
          "id": 201,
          "name": "Twin Stick Shooter",
          "slug": "twin-stick-shooter",
          "language": "eng",
          "games_count": 1465,
          "image_background": "https://media.rawg.io/media/screenshots/fdc/fdc21a8972c4b38fb0e517db7f6e9e23.jpg"
        },
        {
          "id": 411,
          "name": "cooperative",
          "slug": "cooperative",
          "language": "eng",
          "games_count": 2532,
          "image_background": "https://media.rawg.io/media/games/34b/34b1f1850a1c06fd971bc6ab3ac0ce0e.jpg"
        },
        {
          "id": 7808,
          "name": "steam-trading-cards",
          "slug": "steam-trading-cards",
          "language": "eng",
          "games_count": 7605,
          "image_background": "https://media.rawg.io/media/games/d1a/d1a2e99ade53494c6330a0ed945fe823.jpg"
        },
        {
          "id": 42398,
          "name": "Инди",
          "slug": "indi-2",
          "language": "rus",
          "games_count": 32347,
          "image_background": "https://media.rawg.io/media/games/ed5/ed5b7d01dd68fd8d598c91ad61f153af.jpg"
        },
        {
          "id": 42399,
          "name": "Казуальная игра",
          "slug": "kazualnaia-igra",
          "language": "rus",
          "games_count": 17983,
          "image_background": "https://media.rawg.io/media/games/e9c/e9c042d14515eb3ff7cb4db9fe78e435.jpg"
        },
        {
          "id": 42417,
          "name": "Экшен",
          "slug": "ekshen",
          "language": "rus",
          "games_count": 20346,
          "image_background": "https://media.rawg.io/media/games/b8c/b8c243eaa0fbac8115e0cdccac3f91dc.jpg"
        },
        {
          "id": 42560,
          "name": "Разрушения",
          "slug": "razrusheniia",
          "language": "rus",
          "games_count": 334,
          "image_background": "https://media.rawg.io/media/screenshots/41b/41b396a56bcce431dfe1beb920e9faf5.jpg"
        },
        {
          "id": 42605,
          "name": "Танки",
          "slug": "tanki",
          "language": "rus",
          "games_count": 197,
          "image_background": "https://media.rawg.io/media/games/bff/bff077fb7c3b037bd5ed920bf447c863.jpg"
        },
        {
          "id": 42634,
          "name": "Твин-стик шутер",
          "slug": "tvin-stik-shuter",
          "language": "rus",
          "games_count": 402,
          "image_background": "https://media.rawg.io/media/screenshots/c16/c167162530a93902a232389086164fca.jpg"
        }
      ],
      "esrb_rating": null,
      "user_game": null,
      "reviews_count": 1,
      "community_rating": 0,
      "saturated_color": "0f0f0f",
      "dominant_color": "0f0f0f",
      "short_screenshots": [
        {
          "id": -1,
          "image": "https://media.rawg.io/media/screenshots/a92/a92d6549a58f90cada80009c2f20e38c.jpg"
        },
        {
          "id": 104736,
          "image": "https://media.rawg.io/media/screenshots/247/247235bfcc4da5cb5a7adda4a24b0b3c.jpg"
        },
        {
          "id": 104737,
          "image": "https://media.rawg.io/media/screenshots/1f8/1f8b8be4e5562222b11344fda5c26a5a.jpg"
        },
        {
          "id": 104738,
          "image": "https://media.rawg.io/media/screenshots/b1c/b1cc42c28551c7acde0cf7425d7dc215.jpg"
        },
        {
          "id": 104739,
          "image": "https://media.rawg.io/media/screenshots/b65/b65dabfef3530cd31aa6fab83c26a352.jpg"
        },
        {
          "id": 104740,
          "image": "https://media.rawg.io/media/screenshots/58e/58e8b6876904dfd6fa8a008327a9380b.jpg"
        },
        {
          "id": 104741,
          "image": "https://media.rawg.io/media/screenshots/522/522810acdeffc7cb6a84ed0b3d5e2261.jpg"
        }
      ],
      "parent_platforms": [
        {
          "platform": {
            "id": 1,
            "name": "PC",
            "slug": "pc"
          }
        }
      ],
      "genres": [
        {
          "id": 40,
          "name": "Casual",
          "slug": "casual"
        },
        {
          "id": 51,
          "name": "Indie",
          "slug": "indie"
        },
        {
          "id": 4,
          "name": "Action",
          "slug": "action"
        }
      ]
    },
    {
      "slug": "mydream-swift",
      "name": "MyDream Swift",
      "playtime": 1,
      "platforms": [
        {
          "platform": {
            "id": 4,
            "name": "PC",
            "slug": "pc"
          }
        }
      ],
      "stores": [
        {
          "store": {
            "id": 1,
            "name": "Steam",
            "slug": "steam"
          }
        }
      ],
      "released": "2016-04-06",
      "tba": false,
      "background_image": "https://media.rawg.io/media/screenshots/0af/0afaa51328366bc2bffe50448fec7d95.jpg",
      "rating": 0.0,
      "rating_top": 0,
      "ratings": [
        {
          "id": 4,
          "title": "recommended",
          "count": 1,
          "percent": 100.0
        }
      ],
      "ratings_count": 1,
      "reviews_text_count": 0,
      "added": 10,
      "added_by_status": {
        "owned": 10
      },
      "metacritic": null,
      "suggestions_count": 287,
      "updated": "2019-04-22T11:11:02",
      "id": 12515,
      "score": null,
      "clip": null,
      "tags": [
        {
          "id": 156,
          "name": "Software",
          "slug": "software",
          "language": "eng",
          "games_count": 76,
          "image_background": "https://media.rawg.io/media/screenshots/fae/fae55f0e185eff8d10f12341386d13a9.jpg"
        },
        {
          "id": 173,
          "name": "Utilities",
          "slug": "utilities",
          "language": "eng",
          "games_count": 217,
          "image_background": "https://media.rawg.io/media/screenshots/570/5705c9dd0864bfae51c463672110c1e4.jpg"
        },
        {
          "id": 33,
          "name": "VR",
          "slug": "vr",
          "language": "eng",
          "games_count": 7848,
          "image_background": "https://media.rawg.io/media/games/58a/58ac7f6569259dcc0b60b921869b19fc.jpg"
        }
      ],
      "esrb_rating": null,
      "user_game": null,
      "reviews_count": 1,
      "community_rating": 0,
      "saturated_color": "0f0f0f",
      "dominant_color": "0f0f0f",
      "short_screenshots": [
        {
          "id": -1,
          "image": "https://media.rawg.io/media/screenshots/0af/0afaa51328366bc2bffe50448fec7d95.jpg"
        },
        {
          "id": 105135,
          "image": "https://media.rawg.io/media/screenshots/f90/f901cd03e56c7348fff9079897dad303.jpg"
        },
        {
          "id": 105136,
          "image": "https://media.rawg.io/media/screenshots/9c6/9c6e2ccc6465e56fdd23a7d79fa49582.jpg"
        },
        {
          "id": 105137,
          "image": "https://media.rawg.io/media/screenshots/faf/fafe6d68178f2f899fd0cd8ef174c01d.jpg"
        },
        {
          "id": 105138,
          "image": "https://media.rawg.io/media/screenshots/d46/d46a67a11dfb7ad50e10479f94df0c25.jpg"
        },
        {
          "id": 105139,
          "image": "https://media.rawg.io/media/screenshots/a62/a623c6d564c0b27573dfceb152c5628c.jpg"
        },
        {
          "id": 105140,
          "image": "https://media.rawg.io/media/screenshots/f81/f81c6d19037f82180f64ca6634c8217f.jpg"
        }
      ],
      "parent_platforms": [
        {
          "platform": {
            "id": 1,
            "name": "PC",
            "slug": "pc"
          }
        }
      ],
      "genres": []
    },
    {
      "slug": "the-final-frontier-space-simulator",
      "name": "The Final Frontier: Space Simulator",
      "playtime": 1,
      "platforms": [
        {
          "platform": {
            "id": 4,
            "name": "PC",
            "slug": "pc"
          }
        }
      ],
      "stores": [
        {
          "store": {
            "id": 1,
            "name": "Steam",
            "slug": "steam"
          }
        }
      ],
      "released": "2016-06-30",
      "tba": false,
      "background_image": "https://media.rawg.io/media/screenshots/724/724579ad8cd07abc663ed2bbee682f29.jpg",
      "rating": 0.0,
      "rating_top": 0,
      "ratings": [
        {
          "id": 1,
          "title": "skip",
          "count": 1,
          "percent": 100.0
        }
      ],
      "ratings_count": 1,
      "reviews_text_count": 0,
      "added": 5,
      "added_by_status": {
        "owned": 4,
        "dropped": 1
      },
      "metacritic": null,
      "suggestions_count": 267,
      "updated": "2019-01-09T12:41:06",
      "id": 12522,
      "score": null,
      "clip": null,
      "tags": [
        {
          "id": 40845,
          "name": "Partial Controller Support",
          "slug": "partial-controller-support",
          "language": "eng",
          "games_count": 6822,
          "image_background": "https://media.rawg.io/media/games/995/9951d9d55323d08967640f7b9ab3e342.jpg"
        },
        {
          "id": 40847,
          "name": "Steam Achievements",
          "slug": "steam-achievements",
          "language": "eng",
          "games_count": 20092,
          "image_background": "https://media.rawg.io/media/games/d1a/d1a2e99ade53494c6330a0ed945fe823.jpg"
        },
        {
          "id": 14,
          "name": "Early Access",
          "slug": "early-access",
          "language": "eng",
          "games_count": 7090,
          "image_background": "https://media.rawg.io/media/screenshots/654/6540928602af293014efa90d75c420b7.jpg"
        },
        {
          "id": 7,
          "name": "Multiplayer",
          "slug": "multiplayer",
          "language": "eng",
          "games_count": 22719,
          "image_background": "https://media.rawg.io/media/games/34b/34b1f1850a1c06fd971bc6ab3ac0ce0e.jpg"
        },
        {
          "id": 25,
          "name": "Space",
          "slug": "space",
          "language": "eng",
          "games_count": 23212,
          "image_background": "https://media.rawg.io/media/games/ebd/ebdbb7eb52bd58b0e7fa4538d9757b60.jpg"
        }
      ],
      "esrb_rating": null,
      "user_game": null,
      "reviews_count": 1,
      "community_rating": 0,
      "saturated_color": "0f0f0f",
      "dominant_color": "0f0f0f",
      "short_screenshots": [
        {
          "id": -1,
          "image": "https://media.rawg.io/media/screenshots/724/724579ad8cd07abc663ed2bbee682f29.jpg"
        },
        {
          "id": 105233,
          "image": "https://media.rawg.io/media/screenshots/0ac/0ac53259d572dee7d7a1e671fde88c9d.jpg"
        },
        {
          "id": 105234,
          "image": "https://media.rawg.io/media/screenshots/075/0757ae028558e3797106143574b9d555.jpg"
        },
        {
          "id": 105235,
          "image": "https://media.rawg.io/media/screenshots/da7/da7b5f7bb89be8deef6119dbd8951242.jpg"
        },
        {
          "id": 105236,
          "image": "https://media.rawg.io/media/screenshots/dec/dec5d652378c15ebf7ea81b1975fe8c5.jpg"
        },
        {
          "id": 105237,
          "image": "https://media.rawg.io/media/screenshots/c8c/c8cef84ed8363c0b7c8c71f7689f17a3.jpg"
        },
        {
          "id": 105238,
          "image": "https://media.rawg.io/media/screenshots/23c/23ce129db9d411172e75f8272b56b3dc.jpg"
        }
      ],
      "parent_platforms": [
        {
          "platform": {
            "id": 1,
            "name": "PC",
            "slug": "pc"
          }
        }
      ],
      "genres": [
        {
          "id": 59,
          "name": "Massively Multiplayer",
          "slug": "massively-multiplayer"
        },
        {
          "id": 3,
          "name": "Adventure",
          "slug": "adventure"
        },
        {
          "id": 4,
          "name": "Action",
          "slug": "action"
        },
        {
          "id": 14,
          "name": "Simulation",
          "slug": "simulation"
        }
      ]
    },
    {
      "slug": "oxygen-not-included-alpha",
      "name": "Oxygen Not Included - ALPHA",
      "playtime": 0,
      "platforms": [
        {
          "platform": {
            "id": 4,
            "name": "PC",
            "slug": "pc"
          }
        }
      ],
      "stores": [
        {
          "store": {
            "id": 1,
            "name": "Steam",
            "slug": "steam"
          }
        }
      ],
      "released": null,
      "tba": false,
      "background_image": "https://media.rawg.io/media/screenshots/582/582091a03118fe11da6daf322df074cd.jpg",
      "rating": 0.0,
      "rating_top": 0,
      "ratings": [],
      "ratings_count": 0,
      "reviews_text_count": 0,
      "added": 1,
      "added_by_status": {
        "owned": 1
      },
      "metacritic": null,
      "suggestions_count": 284,
      "updated": "2019-08-28T22:13:11",
      "id": 12618,
      "score": null,
      "clip": null,
      "tags": [
        {
          "id": 180,
          "name": "Base Building",
          "slug": "base-building",
          "language": "eng",
          "games_count": 394,
          "image_background": "https://media.rawg.io/media/games/20a/20a1892c6dbe9b820a2f0d79f9ed47a2.jpg"
        },
        {
          "id": 31,
          "name": "Singleplayer",
          "slug": "singleplayer",
          "language": "eng",
          "games_count": 94283,
          "image_background": "https://media.rawg.io/media/games/b7d/b7d3f1715fa8381a4e780173a197a615.jpg"
        },
        {
          "id": 25,
          "name": "Space",
          "slug": "space",
          "language": "eng",
          "games_count": 23212,
          "image_background": "https://media.rawg.io/media/games/ebd/ebdbb7eb52bd58b0e7fa4538d9757b60.jpg"
        },
        {
          "id": 1,
          "name": "Survival",
          "slug": "survival",
          "language": "eng",
          "games_count": 4132,
          "image_background": "https://media.rawg.io/media/games/48e/48e63bbddeddbe9ba81942772b156664.jpg"
        }
      ],
      "esrb_rating": null,
      "user_game": null,
      "reviews_count": 0,
      "community_rating": 0,
      "saturated_color": "0f0f0f",
      "dominant_color": "0f0f0f",
      "short_screenshots": [
        {
          "id": -1,
          "image": "https://media.rawg.io/media/screenshots/582/582091a03118fe11da6daf322df074cd.jpg"
        },
        {
          "id": 106201,
          "image": "https://media.rawg.io/media/screenshots/457/457dca9f409d3cf2a347a64d024a9ec9.jpg"
        },
        {
          "id": 106202,
          "image": "https://media.rawg.io/media/screenshots/1ed/1edc9212e183dbcd1f7387358d47ae17.jpg"
        },
        {
          "id": 106203,
          "image": "https://media.rawg.io/media/screenshots/75c/75c83ce20583ecd1bb5e22d380e32e04.jpg"
        },
        {
          "id": 106204,
          "image": "https://media.rawg.io/media/screenshots/199/199a430bcee64525af5bcdae88ba1c47.jpg"
        },
        {
          "id": 106205,
          "image": "https://media.rawg.io/media/screenshots/582/582091a03118fe11da6daf322df074cd.jpg"
        }
      ],
      "parent_platforms": [
        {
          "platform": {
            "id": 1,
            "name": "PC",
            "slug": "pc"
          }
        }
      ],
      "genres": [
        {
          "id": 51,
          "name": "Indie",
          "slug": "indie"
        },
        {
          "id": 14,
          "name": "Simulation",
          "slug": "simulation"
        }
      ]
    },
    {
      "slug": "electric-zombies",
      "name": "Electric Zombies!",
      "playtime": 0,
      "platforms": [
        {
          "platform": {
            "id": 4,
            "name": "PC",
            "slug": "pc"
          }
        }
      ],
      "stores": [
        {
          "store": {
            "id": 1,
            "name": "Steam",
            "slug": "steam"
          }
        }
      ],
      "released": "2016-06-09",
      "tba": false,
      "background_image": "https://media.rawg.io/media/screenshots/071/0713e935c211482facb3f69c845678be.jpg",
      "rating": 0.0,
      "rating_top": 0,
      "ratings": [],
      "ratings_count": 0,
      "reviews_text_count": 0,
      "added": 2,
      "added_by_status": {
        "owned": 2
      },
      "metacritic": null,
      "suggestions_count": 346,
      "updated": "2019-08-28T22:13:10",
      "id": 12619,
      "score": null,
      "clip": null,
      "tags": [
        {
          "id": 40847,
          "name": "Steam Achievements",
          "slug": "steam-achievements",
          "language": "eng",
          "games_count": 20092,
          "image_background": "https://media.rawg.io/media/games/d1a/d1a2e99ade53494c6330a0ed945fe823.jpg"
        },
        {
          "id": 40849,
          "name": "Steam Cloud",
          "slug": "steam-cloud",
          "language": "eng",
          "games_count": 9361,
          "image_background": "https://media.rawg.io/media/games/328/3283617cb7d75d67257fc58339188742.jpg"
        },
        {
          "id": 31,
          "name": "Singleplayer",
          "slug": "singleplayer",
          "language": "eng",
          "games_count": 94283,
          "image_background": "https://media.rawg.io/media/games/b7d/b7d3f1715fa8381a4e780173a197a615.jpg"
        },
        {
          "id": 7808,
          "name": "steam-trading-cards",
          "slug": "steam-trading-cards",
          "language": "eng",
          "games_count": 7605,
          "image_background": "https://media.rawg.io/media/games/d1a/d1a2e99ade53494c6330a0ed945fe823.jpg"
        }
      ],
      "esrb_rating": null,
      "user_game": null,
      "reviews_count": 0,
      "community_rating": 0,
      "saturated_color": "0f0f0f",
      "dominant_color": "0f0f0f",
      "short_screenshots": [
        {
          "id": -1,
          "image": "https://media.rawg.io/media/screenshots/071/0713e935c211482facb3f69c845678be.jpg"
        },
        {
          "id": 106206,
          "image": "https://media.rawg.io/media/screenshots/3ec/3ecfa9209736763b7f1e4b4ecda24ce5.jpg"
        },
        {
          "id": 106207,
          "image": "https://media.rawg.io/media/screenshots/499/499130166fc7daf096d9b956126ad4b7.jpg"
        },
        {
          "id": 106208,
          "image": "https://media.rawg.io/media/screenshots/96d/96d98671261cc034343a6100c6c37102.jpg"
        },
        {
          "id": 106209,
          "image": "https://media.rawg.io/media/screenshots/edc/edcc12f5a56516ec7d4b11cd8b9cfa32.jpg"
        },
        {
          "id": 106210,
          "image": "https://media.rawg.io/media/screenshots/399/399c60dde3fd649f3fb02eb046d1d140.jpg"
        },
        {
          "id": 106211,
          "image": "https://media.rawg.io/media/screenshots/5c2/5c2e9b25bba03c52b1647813eaed0627.jpg"
        }
      ],
      "parent_platforms": [
        {
          "platform": {
            "id": 1,
            "name": "PC",
            "slug": "pc"
          }
        }
      ],
      "genres": [
        {
          "id": 40,
          "name": "Casual",
          "slug": "casual"
        },
        {
          "id": 51,
          "name": "Indie",
          "slug": "indie"
        },
        {
          "id": 4,
          "name": "Action",
          "slug": "action"
        }
      ]
    },
    {
      "slug": "adrenaline-adventure",
      "name": "Adrenaline Adventure",
      "playtime": 4,
      "platforms": [
        {
          "platform": {
            "id": 4,
            "name": "PC",
            "slug": "pc"
          }
        }
      ],
      "stores": [
        {
          "store": {
            "id": 1,
            "name": "Steam",
            "slug": "steam"
          }
        }
      ],
      "released": "2016-11-17",
      "tba": false,
      "background_image": "https://media.rawg.io/media/screenshots/98b/98b4a82446d55ad5233fddec06cfa5d7.jpg",
      "rating": 0.0,
      "rating_top": 0,
      "ratings": [],
      "ratings_count": 0,
      "reviews_text_count": 0,
      "added": 35,
      "added_by_status": {
        "owned": 35
      },
      "metacritic": null,
      "suggestions_count": 302,
      "updated": "2019-08-28T22:13:09",
      "id": 12673,
      "score": null,
      "clip": null,
      "tags": [
        {
          "id": 31,
          "name": "Singleplayer",
          "slug": "singleplayer",
          "language": "eng",
          "games_count": 94283,
          "image_background": "https://media.rawg.io/media/games/b7d/b7d3f1715fa8381a4e780173a197a615.jpg"
        },
        {
          "id": 7808,
          "name": "steam-trading-cards",
          "slug": "steam-trading-cards",
          "language": "eng",
          "games_count": 7605,
          "image_background": "https://media.rawg.io/media/games/d1a/d1a2e99ade53494c6330a0ed945fe823.jpg"
        },
        {
          "id": 42392,
          "name": "Приключение",
          "slug": "prikliuchenie",
          "language": "rus",
          "games_count": 18381,
          "image_background": "https://media.rawg.io/media/games/bc0/bc06a29ceac58652b684deefe7d56099.jpg"
        },
        {
          "id": 42398,
          "name": "Инди",
          "slug": "indi-2",
          "language": "rus",
          "games_count": 32347,
          "image_background": "https://media.rawg.io/media/games/ed5/ed5b7d01dd68fd8d598c91ad61f153af.jpg"
        },
        {
          "id": 42413,
          "name": "Симулятор",
          "slug": "simuliator",
          "language": "rus",
          "games_count": 9279,
          "image_background": "https://media.rawg.io/media/games/174/1743b3dd185bda4a7be349347d4064df.jpg"
        },
        {
          "id": 42417,
          "name": "Экшен",
          "slug": "ekshen",
          "language": "rus",
          "games_count": 20346,
          "image_background": "https://media.rawg.io/media/games/b8c/b8c243eaa0fbac8115e0cdccac3f91dc.jpg"
        },
        {
          "id": 42496,
          "name": "Гонки",
          "slug": "gonki",
          "language": "rus",
          "games_count": 1762,
          "image_background": "https://media.rawg.io/media/games/1f5/1f5ddf7199f2778ff83663b93b5cb330.jpg"
        }
      ],
      "esrb_rating": null,
      "user_game": null,
      "reviews_count": 0,
      "community_rating": 0,
      "saturated_color": "0f0f0f",
      "dominant_color": "0f0f0f",
      "short_screenshots": [
        {
          "id": -1,
          "image": "https://media.rawg.io/media/screenshots/98b/98b4a82446d55ad5233fddec06cfa5d7.jpg"
        },
        {
          "id": 106781,
          "image": "https://media.rawg.io/media/screenshots/7c8/7c8aa939c9829c17809577ad0b855b07.jpg"
        },
        {
          "id": 106782,
          "image": "https://media.rawg.io/media/screenshots/c0a/c0a7a913fef2fa3ead6d47d17884455e.jpg"
        },
        {
          "id": 106783,
          "image": "https://media.rawg.io/media/screenshots/eda/edadbd9d781f396f3c8660dad3a72259.jpg"
        },
        {
          "id": 106784,
          "image": "https://media.rawg.io/media/screenshots/d3a/d3ae97a5ef2b2b5198ebfb5aeb34e735.jpg"
        },
        {
          "id": 106785,
          "image": "https://media.rawg.io/media/screenshots/13d/13db4801b0fb8a8a4931735d5645c19f.jpg"
        },
        {
          "id": 106786,
          "image": "https://media.rawg.io/media/screenshots/51e/51eea041446af5de94edbe9b322b8e1c.jpg"
        }
      ],
      "parent_platforms": [
        {
          "platform": {
            "id": 1,
            "name": "PC",
            "slug": "pc"
          }
        }
      ],
      "genres": [
        {
          "id": 1,
          "name": "Racing",
          "slug": "racing"
        },
        {
          "id": 3,
          "name": "Adventure",
          "slug": "adventure"
        },
        {
          "id": 4,
          "name": "Action",
          "slug": "action"
        },
        {
          "id": 14,
          "name": "Simulation",
          "slug": "simulation"
        },
        {
          "id": 51,
          "name": "Indie",
          "slug": "indie"
        }
      ]
    },
    {
      "slug": "gowings-safari",
      "name": "GoWings Safari",
      "playtime": 0,
      "platforms": [
        {
          "platform": {
            "id": 4,
            "name": "PC",
            "slug": "pc"
          }
        }
      ],
      "stores": [
        {
          "store": {
            "id": 1,
            "name": "Steam",
            "slug": "steam"
          }
        }
      ],
      "released": "2016-12-23",
      "tba": false,
      "background_image": "https://media.rawg.io/media/screenshots/96f/96f86ca99b6aa691a4981fb8831d093a.jpg",
      "rating": 0.0,
      "rating_top": 0,
      "ratings": [],
      "ratings_count": 0,
      "reviews_text_count": 0,
      "added": 0,
      "added_by_status": null,
      "metacritic": null,
      "suggestions_count": 271,
      "updated": "2019-08-28T22:13:06",
      "id": 12742,
      "score": null,
      "clip": null,
      "tags": [
        {
          "id": 40836,
          "name": "Full controller support",
          "slug": "full-controller-support",
          "language": "eng",
          "games_count": 9473,
          "image_background": "https://media.rawg.io/media/games/310/3106b0e012271c5ffb16497b070be739.jpg"
        },
        {
          "id": 31,
          "name": "Singleplayer",
          "slug": "singleplayer",
          "language": "eng",
          "games_count": 94283,
          "image_background": "https://media.rawg.io/media/games/b7d/b7d3f1715fa8381a4e780173a197a615.jpg"
        },
        {
          "id": 33,
          "name": "VR",
          "slug": "vr",
          "language": "eng",
          "games_count": 7848,
          "image_background": "https://media.rawg.io/media/games/58a/58ac7f6569259dcc0b60b921869b19fc.jpg"
        },
        {
          "id": 42392,
          "name": "Приключение",
          "slug": "prikliuchenie",
          "language": "rus",
          "games_count": 18381,
          "image_background": "https://media.rawg.io/media/games/bc0/bc06a29ceac58652b684deefe7d56099.jpg"
        },
        {
          "id": 42399,
          "name": "Казуальная игра",
          "slug": "kazualnaia-igra",
          "language": "rus",
          "games_count": 17983,
          "image_background": "https://media.rawg.io/media/games/e9c/e9c042d14515eb3ff7cb4db9fe78e435.jpg"
        },
        {
          "id": 42417,
          "name": "Экшен",
          "slug": "ekshen",
          "language": "rus",
          "games_count": 20346,
          "image_background": "https://media.rawg.io/media/games/b8c/b8c243eaa0fbac8115e0cdccac3f91dc.jpg"
        }
      ],
      "esrb_rating": null,
      "user_game": null,
      "reviews_count": 0,
      "community_rating": 0,
      "saturated_color": "0f0f0f",
      "dominant_color": "0f0f0f",
      "short_screenshots": [
        {
          "id": -1,
          "image": "https://media.rawg.io/media/screenshots/96f/96f86ca99b6aa691a4981fb8831d093a.jpg"
        },
        {
          "id": 107678,
          "image": "https://media.rawg.io/media/screenshots/8f8/8f868eca9cd9552a0dc89a06f02b4495.jpg"
        },
        {
          "id": 107679,
          "image": "https://media.rawg.io/media/screenshots/85c/85cd3e37b1c600ae2e1a8a962e496774.jpg"
        },
        {
          "id": 107680,
          "image": "https://media.rawg.io/media/screenshots/3e8/3e86a46b520f363322fe81acef87ce0f.jpg"
        },
        {
          "id": 107681,
          "image": "https://media.rawg.io/media/screenshots/cfe/cfe7c98686d967525824293fa0f48c8b.jpg"
        },
        {
          "id": 107682,
          "image": "https://media.rawg.io/media/screenshots/0ef/0ef31940cd6d9ee6400cc8131e57ef51.jpg"
        },
        {
          "id": 107683,
          "image": "https://media.rawg.io/media/screenshots/4d2/4d2849411bc19c75f6e8d234f34a41b2.jpg"
        }
      ],
      "parent_platforms": [
        {
          "platform": {
            "id": 1,
            "name": "PC",
            "slug": "pc"
          }
        }
      ],
      "genres": [
        {
          "id": 40,
          "name": "Casual",
          "slug": "casual"
        },
        {
          "id": 3,
          "name": "Adventure",
          "slug": "adventure"
        },
        {
          "id": 4,
          "name": "Action",
          "slug": "action"
        }
      ]
    },
    {
      "slug": "space-vr",
      "name": "Space, VR!",
      "playtime": 0,
      "platforms": [
        {
          "platform": {
            "id": 4,
            "name": "PC",
            "slug": "pc"
          }
        }
      ],
      "stores": [
        {
          "store": {
            "id": 1,
            "name": "Steam",
            "slug": "steam"
          }
        }
      ],
      "released": "2017-03-02",
      "tba": false,
      "background_image": "https://media.rawg.io/media/screenshots/fbb/fbb316e8c16f3de90f8a52b6eb6c08bd.jpg",
      "rating": 0.0,
      "rating_top": 0,
      "ratings": [],
      "ratings_count": 0,
      "reviews_text_count": 0,
      "added": 3,
      "added_by_status": {
        "owned": 2,
        "toplay": 1
      },
      "metacritic": null,
      "suggestions_count": 73,
      "updated": "2019-08-28T22:13:02",
      "id": 12865,
      "score": null,
      "clip": null,
      "tags": [
        {
          "id": 31,
          "name": "Singleplayer",
          "slug": "singleplayer",
          "language": "eng",
          "games_count": 94283,
          "image_background": "https://media.rawg.io/media/games/b7d/b7d3f1715fa8381a4e780173a197a615.jpg"
        },
        {
          "id": 25,
          "name": "Space",
          "slug": "space",
          "language": "eng",
          "games_count": 23212,
          "image_background": "https://media.rawg.io/media/games/ebd/ebdbb7eb52bd58b0e7fa4538d9757b60.jpg"
        },
        {
          "id": 33,
          "name": "VR",
          "slug": "vr",
          "language": "eng",
          "games_count": 7848,
          "image_background": "https://media.rawg.io/media/games/58a/58ac7f6569259dcc0b60b921869b19fc.jpg"
        },
        {
          "id": 42398,
          "name": "Инди",
          "slug": "indi-2",
          "language": "rus",
          "games_count": 32347,
          "image_background": "https://media.rawg.io/media/games/ed5/ed5b7d01dd68fd8d598c91ad61f153af.jpg"
        },
        {
          "id": 42422,
          "name": "Космос",
          "slug": "kosmos-2",
          "language": "rus",
          "games_count": 1538,
          "image_background": "https://media.rawg.io/media/screenshots/120/120d930368bc171c42f9caab94e33c65.jpg"
        }
      ],
      "esrb_rating": null,
      "user_game": null,
      "reviews_count": 0,
      "community_rating": 0,
      "saturated_color": "0f0f0f",
      "dominant_color": "0f0f0f",
      "short_screenshots": [
        {
          "id": -1,
          "image": "https://media.rawg.io/media/screenshots/fbb/fbb316e8c16f3de90f8a52b6eb6c08bd.jpg"
        },
        {
          "id": 108985,
          "image": "https://media.rawg.io/media/screenshots/7c5/7c530ea48840c1866b6394580e2d479c.jpg"
        },
        {
          "id": 108986,
          "image": "https://media.rawg.io/media/screenshots/fbb/fbb316e8c16f3de90f8a52b6eb6c08bd.jpg"
        }
      ],
      "parent_platforms": [
        {
          "platform": {
            "id": 1,
            "name": "PC",
            "slug": "pc"
          }
        }
      ],
      "genres": [
        {
          "id": 51,
          "name": "Indie",
          "slug": "indie"
        }
      ]
    },
    {
      "slug": "containment-protocol",
      "name": "Containment Protocol",
      "playtime": 0,
      "platforms": [
        {
          "platform": {
            "id": 4,
            "name": "PC",
            "slug": "pc"
          }
        },
        {
          "platform": {
            "id": 5,
            "name": "macOS",
            "slug": "macos"
          }
        }
      ],
      "stores": [
        {
          "store": {
            "id": 1,
            "name": "Steam",
            "slug": "steam"
          }
        }
      ],
      "released": "2015-08-31",
      "tba": false,
      "background_image": "https://media.rawg.io/media/screenshots/c1e/c1ea338978acd0bf5d804364feeeff34.jpg",
      "rating": 0.0,
      "rating_top": 0,
      "ratings": [],
      "ratings_count": 0,
      "reviews_text_count": 0,
      "added": 7,
      "added_by_status": {
        "owned": 7
      },
      "metacritic": null,
      "suggestions_count": 92,
      "updated": "2019-08-28T22:13:02",
      "id": 12868,
      "score": null,
      "clip": null,
      "tags": [
        {
          "id": 40845,
          "name": "Partial Controller Support",
          "slug": "partial-controller-support",
          "language": "eng",
          "games_count": 6822,
          "image_background": "https://media.rawg.io/media/games/995/9951d9d55323d08967640f7b9ab3e342.jpg"
        },
        {
          "id": 14,
          "name": "Early Access",
          "slug": "early-access",
          "language": "eng",
          "games_count": 7090,
          "image_background": "https://media.rawg.io/media/screenshots/654/6540928602af293014efa90d75c420b7.jpg"
        },
        {
          "id": 31,
          "name": "Singleplayer",
          "slug": "singleplayer",
          "language": "eng",
          "games_count": 94283,
          "image_background": "https://media.rawg.io/media/games/b7d/b7d3f1715fa8381a4e780173a197a615.jpg"
        },
        {
          "id": 42392,
          "name": "Приключение",
          "slug": "prikliuchenie",
          "language": "rus",
          "games_count": 18381,
          "image_background": "https://media.rawg.io/media/games/bc0/bc06a29ceac58652b684deefe7d56099.jpg"
        },
        {
          "id": 42398,
          "name": "Инди",
          "slug": "indi-2",
          "language": "rus",
          "games_count": 32347,
          "image_background": "https://media.rawg.io/media/games/ed5/ed5b7d01dd68fd8d598c91ad61f153af.jpg"
        },
        {
          "id": 42411,
          "name": "Ранний доступ",
          "slug": "rannii-dostup",
          "language": "rus",
          "games_count": 6608,
          "image_background": "https://media.rawg.io/media/games/e4a/e4ab7f784bdc38c76ce6e4cef9715d18.jpg"
        },
        {
          "id": 42417,
          "name": "Экшен",
          "slug": "ekshen",
          "language": "rus",
          "games_count": 20346,
          "image_background": "https://media.rawg.io/media/games/b8c/b8c243eaa0fbac8115e0cdccac3f91dc.jpg"
        }
      ],
      "esrb_rating": null,
      "user_game": null,
      "reviews_count": 0,
      "community_rating": 0,
      "saturated_color": "0f0f0f",
      "dominant_color": "0f0f0f",
      "short_screenshots": [
        {
          "id": -1,
          "image": "https://media.rawg.io/media/screenshots/c1e/c1ea338978acd0bf5d804364feeeff34.jpg"
        },
        {
          "id": 109006,
          "image": "https://media.rawg.io/media/screenshots/8f4/8f456add67d9209b0fc6f9d6b0f3047e.jpg"
        },
        {
          "id": 109007,
          "image": "https://media.rawg.io/media/screenshots/7f0/7f049c92cd15639b7be0ab654842ad91.jpg"
        },
        {
          "id": 109008,
          "image": "https://media.rawg.io/media/screenshots/ec7/ec7c8e4678d69a474e7221539d2ed7a3.jpg"
        },
        {
          "id": 109009,
          "image": "https://media.rawg.io/media/screenshots/323/32353990dd2c956a62bf565d325e7794.jpg"
        },
        {
          "id": 109010,
          "image": "https://media.rawg.io/media/screenshots/edf/edfcf39f5ebe8378c5e691fbc45491a8.jpg"
        },
        {
          "id": 109011,
          "image": "https://media.rawg.io/media/screenshots/e3b/e3b6ea347e4dcf72748c5d878a2215e2.jpg"
        }
      ],
      "parent_platforms": [
        {
          "platform": {
            "id": 1,
            "name": "PC",
            "slug": "pc"
          }
        },
        {
          "platform": {
            "id": 5,
            "name": "Apple Macintosh",
            "slug": "mac"
          }
        }
      ],
      "genres": [
        {
          "id": 51,
          "name": "Indie",
          "slug": "indie"
        },
        {
          "id": 3,
          "name": "Adventure",
          "slug": "adventure"
        },
        {
          "id": 4,
          "name": "Action",
          "slug": "action"
        }
      ]
    }
  ],
  "user_platforms": false
}
